[
  {
    "country": "Albania",
    "wave1": "44,9"
  },
  {
    "country": "Azerbaijan",
    "wave1": "81,7"
  },
  {
    "country": "Argentina",
    "wave1": "75,7"
  },
  {
    "country": "Australia",
    "wave1": "88,8"
  },
  {
    "country": "Bangladesh",
    "wave1": "58,6"
  },
  {
    "country": "Armenia",
    "wave1": "70,4"
  },
  {
    "country": "Brazil",
    "wave1": "90,9"
  },
  {
    "country": "Bulgaria",
    "wave1": "58,9"
  },
  {
    "country": "Belarus",
    "wave1": "73,1"
  },
  {
    "country": "Chile",
    "wave1": "85,6"
  },
  {
    "country": "China",
    "wave1": "54,6"
  },
  {
    "country": "Taiwan",
    "wave1": "77,6"
  },
  {
    "country": "Colombia",
    "wave1": "88,2"
  },
  {
    "country": "Croatia",
    "wave1": "75,5"
  },
  {
    "country": "Czech Rep.",
    "wave1": "74,2"
  },
  {
    "country": "Dominican Rep.",
    "wave1": "66,9"
  },
  {
    "country": "El Salvador",
    "wave1": "88,5"
  },
  {
    "country": "Estonia",
    "wave1": 75
  },
  {
    "country": "Finland",
    "wave1": "90,3"
  },
  {
    "country": "Georgia",
    "wave1": 81
  },
  {
    "country": "Germany",
    "wave1": "86,7"
  },
  {
    "country": "Hungary",
    "wave1": "74,9"
  },
  {
    "country": "India",
    "wave1": 36
  },
  {
    "country": "Japan",
    "wave1": "88,9"
  },
  {
    "country": "South Korea",
    "wave1": "85,5"
  },
  {
    "country": "Latvia",
    "wave1": "64,5"
  },
  {
    "country": "Lithuania",
    "wave1": "72,6"
  },
  {
    "country": "Mexico",
    "wave1": 72
  },
  {
    "country": "Moldova",
    "wave1": "68,2"
  },
  {
    "country": "New Zealand",
    "wave1": "88,5"
  },
  {
    "country": "Nigeria",
    "wave1": "82,6"
  },
  {
    "country": "Norway",
    "wave1": "91,4"
  },
  {
    "country": "Pakistan",
    "wave1": 39
  },
  {
    "country": "Peru",
    "wave1": "66,5"
  },
  {
    "country": "Philippines",
    "wave1": "55,6"
  },
  {
    "country": "Poland",
    "wave1": "77,9"
  },
  {
    "country": "Puerto Rico",
    "wave1": "88,4"
  },
  {
    "country": "Romania",
    "wave1": "72,4"
  },
  {
    "country": "Russia",
    "wave1": "70,3"
  },
  {
    "country": "Slovakia",
    "wave1": "80,6"
  },
  {
    "country": "Slovenia",
    "wave1": "77,7"
  },
  {
    "country": "South Africa",
    "wave1": "71,2"
  },
  {
    "country": "Spain",
    "wave1": "82,2"
  },
  {
    "country": "Sweden",
    "wave1": "94,4"
  },
  {
    "country": "Switzerland",
    "wave1": "88,2"
  },
  {
    "country": "Turkey",
    "wave1": "78,4"
  },
  {
    "country": "Ukraine",
    "wave1": "69,1"
  },
  {
    "country": "Macedonia",
    "wave1": "78,4"
  },
  {
    "country": "United States",
    "wave1": 88
  },
  {
    "country": "Uruguay",
    "wave1": "87,7"
  },
  {
    "country": "Venezuela",
    "wave1": "86,8"
  },
  {
    "country": "Serbia",
    "wave1": "71,5"
  },
  {
    "country": "Montenegro",
    "wave1": "71,6"
  },
  {
    "country": "Bosnia",
    "wave1": "88,5"
  }
]